kepler_raster_server/__init__.py
kepler_raster_server/main.py
kepler_raster_server/extensions/mosaic/__init__.py
kepler_raster_server/extensions/mosaic/dependency.py
kepler_raster_server/extensions/mosaic/mosaic_backend.py
kepler_raster_server/extensions/mosaic/tiler_factory.py
kepler_raster_server/extensions/mosaic/utils.py
kepler_raster_server/extensions/terrain/__init__.py
kepler_raster_server/extensions/terrain/terrain.py
kepler_raster_server/extensions/terrain/terrain_responses.py
kepler_raster_server-0.0.11.dist-info/licenses/LICENSE
kepler_raster_server-0.0.11.dist-info/METADATA
kepler_raster_server-0.0.11.dist-info/WHEEL
kepler_raster_server-0.0.11.dist-info/top_level.txt
kepler_raster_server-0.0.11.dist-info/RECORD
