Metadata-Version: 2.4
Name: kepler-raster-server
Version: 0.0.11
Summary: A Python package for serving Kepler raster tiles
Author-email: Your Name <your@email.com>
License: MIT License
Project-URL: Homepage, https://github.com/igorDykhta/kepler-titiler-tests
Project-URL: Documentation, https://github.com/igorDykhta/kepler-titiler-tests
Project-URL: Issues, https://github.com/igorDykhta/kepler-titiler-tests/issues
Project-URL: Source, https://github.com/igorDykhta/kepler-titiler-tests
Project-URL: Changelog, https://github.com/igorDykhta/kepler-titiler-tests/changelog
Keywords: Kepler.gl,Raster Layer
Requires-Python: >=3.9
License-File: LICENSE
Requires-Dist: fastapi<1.0,>=0.100.0
Requires-Dist: titiler.core==0.22.1
Requires-Dist: titiler.xarray==0.22.1
Requires-Dist: titiler.extensions==0.22.1
Requires-Dist: titiler.mosaic==0.22.1
Requires-Dist: titiler.application==0.22.1
Requires-Dist: quantized-mesh-encoder>=0.4.3
Requires-Dist: pymartini>=0.4.4
Requires-Dist: pydelatin>=0.2.7
Requires-Dist: morecantile>=3.2.5
Requires-Dist: planetary_computer>=0.2.2
Requires-Dist: numpy==1.26.4
Dynamic: license-file
